aleph/__init__.py
aleph/alef_cli.py
aleph/cli.py
aleph/config.py
aleph/core.py
aleph/types.py
aleph/cache/__init__.py
aleph/cache/base.py
aleph/cache/memory.py
aleph/mcp/__init__.py
aleph/mcp/actions.py
aleph/mcp/env_utils.py
aleph/mcp/formatting.py
aleph/mcp/io_utils.py
aleph/mcp/local_server.py
aleph/mcp/remote.py
aleph/mcp/server.py
aleph/mcp/session.py
aleph/mcp/tool_registry.py
aleph/mcp/workspace.py
aleph/prompts/__init__.py
aleph/prompts/system.py
aleph/providers/__init__.py
aleph/providers/anthropic.py
aleph/providers/base.py
aleph/providers/cli.py
aleph/providers/http_base.py
aleph/providers/http_utils.py
aleph/providers/openai.py
aleph/providers/registry.py
aleph/repl/__init__.py
aleph/repl/helpers.py
aleph/repl/sandbox.py
aleph/sub_query/__init__.py
aleph/sub_query/api_backend.py
aleph/sub_query/cli_backend.py
aleph/swarm/__init__.py
aleph/swarm/coordination.py
aleph/utils/__init__.py
aleph/utils/logging.py
aleph/utils/tokens.py
aleph_rlm-0.7.10.dist-info/METADATA
aleph_rlm-0.7.10.dist-info/WHEEL
aleph_rlm-0.7.10.dist-info/entry_points.txt
aleph_rlm-0.7.10.dist-info/licenses/LICENSE
aleph_rlm-0.7.10.dist-info/RECORD
